docopt/__init__.py
libcst/__init__.py
libcst/_add_slots.py
libcst/_batched_visitor.py
libcst/_exceptions.py
libcst/_flatten_sentinel.py
libcst/_maybe_sentinel.py
libcst/_metadata_dependent.py
libcst/_position.py
libcst/_removal_sentinel.py
libcst/_tabs.py
libcst/_type_enforce.py
libcst/_typed_visitor.py
libcst/_typed_visitor_base.py
libcst/_types.py
libcst/_version.py
libcst/_visitors.py
libcst/py.typed
libcst/tool.py
libcst/_nodes/__init__.py
libcst/_nodes/base.py
libcst/_nodes/deep_equals.py
libcst/_nodes/expression.py
libcst/_nodes/internal.py
libcst/_nodes/module.py
libcst/_nodes/op.py
libcst/_nodes/statement.py
libcst/_nodes/whitespace.py
libcst/_parser/__init__.py
libcst/_parser/base_parser.py
libcst/_parser/custom_itertools.py
libcst/_parser/detect_config.py
libcst/_parser/entrypoints.py
libcst/_parser/grammar.py
libcst/_parser/production_decorator.py
libcst/_parser/python_parser.py
libcst/_parser/whitespace_parser.py
libcst/_parser/wrapped_tokenize.py
libcst/_parser/conversions/__init__.py
libcst/_parser/conversions/expression.py
libcst/_parser/conversions/module.py
libcst/_parser/conversions/params.py
libcst/_parser/conversions/statement.py
libcst/_parser/conversions/terminals.py
libcst/_parser/parso/__init__.py
libcst/_parser/parso/utils.py
libcst/_parser/parso/pgen2/__init__.py
libcst/_parser/parso/pgen2/generator.py
libcst/_parser/parso/pgen2/grammar_parser.py
libcst/_parser/parso/python/__init__.py
libcst/_parser/parso/python/token.py
libcst/_parser/parso/python/tokenize.py
libcst/_parser/types/__init__.py
libcst/_parser/types/config.py
libcst/_parser/types/conversions.py
libcst/_parser/types/partials.py
libcst/_parser/types/production.py
libcst/_parser/types/token.py
libcst/_parser/types/whitespace_state.py
libcst/codegen/__init__.py
libcst/codegen/gather.py
libcst/codegen/gen_matcher_classes.py
libcst/codegen/gen_type_mapping.py
libcst/codegen/gen_visitor_functions.py
libcst/codegen/generate.py
libcst/codegen/transforms.py
libcst/codemod/__init__.py
pandas_tutor-2.0.4.dist-info/METADATA
pandas_tutor-2.0.4.dist-info/WHEEL
pandas_tutor-2.0.4.dist-info/top_level.txt
pandas_tutor-2.0.4.dist-info/RECORD
