Metadata-Version: 2.1
Name: pandas_tutor
Version: 2.0.4
Requires-Dist: pandas >=1.3
Requires-Dist: mypy-extensions ==0.4.3
Requires-Dist: typing-extensions <5.0,>=4.1
